{"nodes": [{"id": "c_users_tanmay_gundre_desktop_erp_1_school_wa_backend_db_queries_leadqueries_js", "label": "leadQueries.js", "file_type": "code", "source_file": "C:\\Users\\TANMAY GUNDRE\\Desktop\\erp_1\\School_WA\\backend\\db\\queries\\leadQueries.js", "source_location": "L1"}, {"id": "queries_leadqueries_createlead", "label": "createLead()", "file_type": "code", "source_file": "C:\\Users\\TANMAY GUNDRE\\Desktop\\erp_1\\School_WA\\backend\\db\\queries\\leadQueries.js", "source_location": "L18"}, {"id": "queries_leadqueries_getallleads", "label": "getAllLeads()", "file_type": "code", "source_file": "C:\\Users\\TANMAY GUNDRE\\Desktop\\erp_1\\School_WA\\backend\\db\\queries\\leadQueries.js", "source_location": "L49"}, {"id": "queries_leadqueries_getleadbyid", "label": "getLeadById()", "file_type": "code", "source_file": "C:\\Users\\TANMAY GUNDRE\\Desktop\\erp_1\\School_WA\\backend\\db\\queries\\leadQueries.js", "source_location": "L95"}, {"id": "queries_leadqueries_updatelead", "label": "updateLead()", "file_type": "code", "source_file": "C:\\Users\\TANMAY GUNDRE\\Desktop\\erp_1\\School_WA\\backend\\db\\queries\\leadQueries.js", "source_location": "L109"}, {"id": "queries_leadqueries_deletelead", "label": "deleteLead()", "file_type": "code", "source_file": "C:\\Users\\TANMAY GUNDRE\\Desktop\\erp_1\\School_WA\\backend\\db\\queries\\leadQueries.js", "source_location": "L148"}, {"id": "queries_leadqueries_getupcomingfollowups", "label": "getUpcomingFollowups()", "file_type": "code", "source_file": "C:\\Users\\TANMAY GUNDRE\\Desktop\\erp_1\\School_WA\\backend\\db\\queries\\leadQueries.js", "source_location": "L170"}], "edges": [{"source": "c_users_tanmay_gundre_desktop_erp_1_school_wa_backend_db_queries_leadqueries_js", "target": "c_users_tanmay_gundre_desktop_erp_1_school_wa_backend_db_pool_ts", "relation": "imports_from", "confidence": "EXTRACTED", "source_file": "C:\\Users\\TANMAY GUNDRE\\Desktop\\erp_1\\School_WA\\backend\\db\\queries\\leadQueries.js", "source_location": "L8", "weight": 1.0}, {"source": "c_users_tanmay_gundre_desktop_erp_1_school_wa_backend_db_queries_leadqueries_js", "target": "queries_leadqueries_createlead", "relation": "contains", "confidence": "EXTRACTED", "source_file": "C:\\Users\\TANMAY GUNDRE\\Desktop\\erp_1\\School_WA\\backend\\db\\queries\\leadQueries.js", "source_location": "L18", "weight": 1.0}, {"source": "c_users_tanmay_gundre_desktop_erp_1_school_wa_backend_db_queries_leadqueries_js", "target": "queries_leadqueries_getallleads", "relation": "contains", "confidence": "EXTRACTED", "source_file": "C:\\Users\\TANMAY GUNDRE\\Desktop\\erp_1\\School_WA\\backend\\db\\queries\\leadQueries.js", "source_location": "L49", "weight": 1.0}, {"source": "c_users_tanmay_gundre_desktop_erp_1_school_wa_backend_db_queries_leadqueries_js", "target": "queries_leadqueries_getleadbyid", "relation": "contains", "confidence": "EXTRACTED", "source_file": "C:\\Users\\TANMAY GUNDRE\\Desktop\\erp_1\\School_WA\\backend\\db\\queries\\leadQueries.js", "source_location": "L95", "weight": 1.0}, {"source": "c_users_tanmay_gundre_desktop_erp_1_school_wa_backend_db_queries_leadqueries_js", "target": "queries_leadqueries_updatelead", "relation": "contains", "confidence": "EXTRACTED", "source_file": "C:\\Users\\TANMAY GUNDRE\\Desktop\\erp_1\\School_WA\\backend\\db\\queries\\leadQueries.js", "source_location": "L109", "weight": 1.0}, {"source": "c_users_tanmay_gundre_desktop_erp_1_school_wa_backend_db_queries_leadqueries_js", "target": "queries_leadqueries_deletelead", "relation": "contains", "confidence": "EXTRACTED", "source_file": "C:\\Users\\TANMAY GUNDRE\\Desktop\\erp_1\\School_WA\\backend\\db\\queries\\leadQueries.js", "source_location": "L148", "weight": 1.0}, {"source": "c_users_tanmay_gundre_desktop_erp_1_school_wa_backend_db_queries_leadqueries_js", "target": "queries_leadqueries_getupcomingfollowups", "relation": "contains", "confidence": "EXTRACTED", "source_file": "C:\\Users\\TANMAY GUNDRE\\Desktop\\erp_1\\School_WA\\backend\\db\\queries\\leadQueries.js", "source_location": "L170", "weight": 1.0}], "raw_calls": [{"caller_nid": "queries_leadqueries_createlead", "callee": "query", "is_member_call": true, "source_file": "C:\\Users\\TANMAY GUNDRE\\Desktop\\erp_1\\School_WA\\backend\\db\\queries\\leadQueries.js", "source_location": "L33"}, {"caller_nid": "queries_leadqueries_getallleads", "callee": "push", "is_member_call": true, "source_file": "C:\\Users\\TANMAY GUNDRE\\Desktop\\erp_1\\School_WA\\backend\\db\\queries\\leadQueries.js", "source_location": "L56"}, {"caller_nid": "queries_leadqueries_getallleads", "callee": "push", "is_member_call": true, "source_file": "C:\\Users\\TANMAY GUNDRE\\Desktop\\erp_1\\School_WA\\backend\\db\\queries\\leadQueries.js", "source_location": "L60"}, {"caller_nid": "queries_leadqueries_getallleads", "callee": "push", "is_member_call": true, "source_file": "C:\\Users\\TANMAY GUNDRE\\Desktop\\erp_1\\School_WA\\backend\\db\\queries\\leadQueries.js", "source_location": "L64"}, {"caller_nid": "queries_leadqueries_getallleads", "callee": "push", "is_member_call": true, "source_file": "C:\\Users\\TANMAY GUNDRE\\Desktop\\erp_1\\School_WA\\backend\\db\\queries\\leadQueries.js", "source_location": "L68"}, {"caller_nid": "queries_leadqueries_getallleads", "callee": "isInteger", "is_member_call": true, "source_file": "C:\\Users\\TANMAY GUNDRE\\Desktop\\erp_1\\School_WA\\backend\\db\\queries\\leadQueries.js", "source_location": "L79"}, {"caller_nid": "queries_leadqueries_getallleads", "callee": "push", "is_member_call": true, "source_file": "C:\\Users\\TANMAY GUNDRE\\Desktop\\erp_1\\School_WA\\backend\\db\\queries\\leadQueries.js", "source_location": "L80"}, {"caller_nid": "queries_leadqueries_getallleads", "callee": "query", "is_member_call": true, "source_file": "C:\\Users\\TANMAY GUNDRE\\Desktop\\erp_1\\School_WA\\backend\\db\\queries\\leadQueries.js", "source_location": "L84"}, {"caller_nid": "queries_leadqueries_getleadbyid", "callee": "query", "is_member_call": true, "source_file": "C:\\Users\\TANMAY GUNDRE\\Desktop\\erp_1\\School_WA\\backend\\db\\queries\\leadQueries.js", "source_location": "L97"}, {"caller_nid": "queries_leadqueries_updatelead", "callee": "query", "is_member_call": true, "source_file": "C:\\Users\\TANMAY GUNDRE\\Desktop\\erp_1\\School_WA\\backend\\db\\queries\\leadQueries.js", "source_location": "L133"}, {"caller_nid": "queries_leadqueries_deletelead", "callee": "query", "is_member_call": true, "source_file": "C:\\Users\\TANMAY GUNDRE\\Desktop\\erp_1\\School_WA\\backend\\db\\queries\\leadQueries.js", "source_location": "L150"}, {"caller_nid": "queries_leadqueries_getupcomingfollowups", "callee": "query", "is_member_call": true, "source_file": "C:\\Users\\TANMAY GUNDRE\\Desktop\\erp_1\\School_WA\\backend\\db\\queries\\leadQueries.js", "source_location": "L203"}]}